{"cameraMode":{"drawMode":0,"name":"Shaded","section":"Shading Mode"},"sceneLighting":true,"audioPlay":false,"sceneViewState":{"showFog":true,"showMaterialUpdate":false,"showSkybox":true,"showFlares":true,"showImageEffects":true,"showParticleSystems":true},"in2DMode":false,"pivot":{"x":46.643768310546878,"y":2.8167877197265627,"z":53.93009948730469},"rotation":{"x":-0.295048326253891,"y":0.6643952131271362,"z":-0.32365110516548159,"w":-0.6056572794914246},"size":32.34138488769531,"orthographic":false}